{"cameraMode":{"drawMode":0,"name":"Shaded","section":"Shading Mode"},"sceneLighting":false,"audioPlay":false,"sceneViewState":{"showFog":true,"showMaterialUpdate":false,"showSkybox":false,"showFlares":true,"showImageEffects":true,"showParticleSystems":true},"in2DMode":false,"pivot":{"x":6.181002140045166,"y":1.1981394290924073,"z":-4.628778457641602},"rotation":{"x":-0.3915218412876129,"y":0.010210244916379452,"z":-0.0043459865264594559,"w":-0.9201045632362366},"size":1.334852933883667,"orthographic":false}